puristaa/__init__.py
puristaa/__main__.py
puristaa/cli.py
puristaa/puristaa.py
test/__init__.py
test/context.py
test/test_cli.py
test/test_puristaa.py
puristaa-2022.7.24.dist-info/LICENSE
puristaa-2022.7.24.dist-info/METADATA
puristaa-2022.7.24.dist-info/WHEEL
puristaa-2022.7.24.dist-info/entry_points.txt
puristaa-2022.7.24.dist-info/top_level.txt
puristaa-2022.7.24.dist-info/RECORD
