Metadata-Version: 2.1
Name: puristaa
Version: 2022.7.24
Summary: Puristaa (Finnish for compress) - shared prefix compression of ordered string sequences.
Home-page: https://git.sr.ht/~sthagen/puristaa
Author: Stefan Hagen
Author-email: stefan@hagen.link
Maintainer: Stefan Hagen
Maintainer-email: stefan@hagen.link
Project-URL: Bug Tracker, https://todo.sr.ht/~sthagen/puristaa
Project-URL: Documentation, https://sthagen.github.io/puristaa
Project-URL: Source Code, https://git.sr.ht/~sthagen/puristaa
Project-URL: Test Coverage, https://codes.dilettant.life/coverage/puristaa
Keywords: compression,developer-tools,text-processing
Classifier: Development Status :: 4 - Beta
Classifier: Intended Audience :: Developers
Classifier: License :: OSI Approved :: MIT License
Classifier: Programming Language :: Python :: 3.10
Classifier: Programming Language :: Python :: 3.8
Classifier: Programming Language :: Python :: 3.9
Classifier: Topic :: Software Development :: Build Tools
Requires-Python: >=3.8
License-File: LICENSE
Provides-Extra: dev
Requires-Dist: black ; extra == 'dev'
Requires-Dist: coverage ; extra == 'dev'
Requires-Dist: flake8 ; extra == 'dev'
Requires-Dist: mypy ; extra == 'dev'
Requires-Dist: pytest ; extra == 'dev'
Requires-Dist: pytest-cov ; extra == 'dev'
Requires-Dist: pytest-flake8 ; extra == 'dev'
